meteo_lt/__init__.py
meteo_lt/api.py
meteo_lt/client.py
meteo_lt/const.py
meteo_lt/models.py
meteo_lt/utils.py
meteo_lt/warnings.py
meteo_lt_pkg-0.4.0.dist-info/licenses/LICENSE
meteo_lt_pkg-0.4.0.dist-info/METADATA
meteo_lt_pkg-0.4.0.dist-info/WHEEL
meteo_lt_pkg-0.4.0.dist-info/top_level.txt
meteo_lt_pkg-0.4.0.dist-info/RECORD
