Metadata-Version: 2.4
Name: meteo_lt-pkg
Version: 0.4.0
Summary: A library to fetch weather data from api.meteo.lt
Author-email: Brunas <brunonas@gmail.com>
Project-URL: Homepage, https://github.com/Brunas/meteo_lt-pkg
Project-URL: Issues, https://github.com/Brunas/meteo_lt-pkg/issues
Classifier: Programming Language :: Python :: 3
Classifier: License :: OSI Approved :: MIT License
Classifier: Operating System :: OS Independent
Classifier: Development Status :: 4 - Beta
Requires-Python: >=3.10
License-File: LICENSE
Requires-Dist: aiohttp
Provides-Extra: dev
Requires-Dist: pytest; extra == "dev"
Requires-Dist: pytest-cov; extra == "dev"
Requires-Dist: pytest-asyncio; extra == "dev"
Requires-Dist: black; extra == "dev"
Requires-Dist: coverage; extra == "dev"
Requires-Dist: flake8; extra == "dev"
Requires-Dist: pyflakes; extra == "dev"
Requires-Dist: pylint; extra == "dev"
Requires-Dist: build; extra == "dev"
Dynamic: license-file
